{"n_records": {"output_type": "display_data", "metadata": {"scrapbook": {"name": "n_records", "mime_prefix": ""}}, "data": {"text/plain": "1546"}}, "pathologies": {"output_type": "display_data", "metadata": {"scrapbook": {"name": "pathologies", "mime_prefix": ""}}, "data": {"text/plain": "                     pathology  patient_id\n0                       BENIGN         258\n1      BENIGN_WITHOUT_CALLBACK          82\n2                    MALIGNANT         276\nTotal                                  616", "text/html": "<div>\n<style scoped>\n    .dataframe tbody tr th:only-of-type {\n        vertical-align: middle;\n    }\n\n    .dataframe tbody tr th {\n        vertical-align: top;\n    }\n\n    .dataframe thead th {\n        text-align: right;\n    }\n</style>\n<table border=\"1\" class=\"dataframe\">\n  <thead>\n    <tr style=\"text-align: right;\">\n      <th></th>\n      <th>pathology</th>\n      <th>patient_id</th>\n    </tr>\n  </thead>\n  <tbody>\n    <tr>\n      <th>0</th>\n      <td>BENIGN</td>\n      <td>258</td>\n    </tr>\n    <tr>\n      <th>1</th>\n      <td>BENIGN_WITHOUT_CALLBACK</td>\n      <td>82</td>\n    </tr>\n    <tr>\n      <th>2</th>\n      <td>MALIGNANT</td>\n      <td>276</td>\n    </tr>\n    <tr>\n      <th>Total</th>\n      <td></td>\n      <td>616</td>\n    </tr>\n  </tbody>\n</table>\n</div>"}}, "n_cases": {"output_type": "display_data", "metadata": {"scrapbook": {"name": "n_cases", "mime_prefix": ""}}, "data": {"text/plain": "602"}}, "n_cases_multiple_pathologies": {"output_type": "display_data", "metadata": {"scrapbook": {"name": "n_cases_multiple_pathologies", "mime_prefix": ""}}, "data": {"text/plain": "14"}}}